baud_rate_generator/baud_rate_generator.v
`timescale 1ns / 1ps
//////////////////////////////////////////////////////////////////////////////////
// Company: 
// Engineer: 
// 
// Create Date:    22:05:50 01/26/2026 
// Design Name: 
// Module Name:    baud_rate_generator 
// Project Name: 
// Target Devices: 
// Tool versions: 
// Description: 
//
// Dependencies: 
//
// Revision: 
// Revision 0.01 - File Created
// Additional Comments: 
//
//////////////////////////////////////////////////////////////////////////////////

module baud_rate_generator(
    input clk_in,
    input start,            //Pino de ativação da cadeia de FFs
    output reg clk_0_out,   //Clock de 100Mhz       1/1
    output reg clk_1_out,   //Clock de 50Mhz        1/2
    output reg clk_2_out,   //Clock de 25Mhz        1/4
    output reg clk_3_out,   //Clock de 12.5Mhz      1/8
    output reg clk_4_out,   //Clock de 6.25Mhz      1/16
    output reg clk_5_out,   //Clock de 3.125Mhz     1/32    (A principio clocks reserva)
    output reg clk_6_out,    //Clock de 1.5625Mhz    1/64    (A principio clocks reserva)
    output reg clk_7_out    //Clock de 1.5625Mhz    1/128   (A principio clocks reserva)
);

reg [7:0] clk_sys;

always@(posedge clk_in)
    begin
        if(start)
            begin
                clk_sys <= clk_sys + 1'b1;
            end
        else 
            begin
                clk_sys <= 1'b0;
            end
    end

always@(*)
    begin
        clk_0_out = clk_sys[0];
        clk_1_out = clk_sys[1];   
        clk_2_out = clk_sys[2]; 
        clk_3_out = clk_sys[3];   
        clk_4_out = clk_sys[4];  
        clk_5_out = clk_sys[5];   
        clk_6_out = clk_sys[6];
        clk_7_out = clk_sys[7];
    end

endmodule

baud_rate_generator/testbench.v
`timescale 1ns / 1ps

////////////////////////////////////////////////////////////////////////////////
// Company: 
// Engineer:
//
// Create Date:   22:12:27 01/26/2026
// Design Name:   baud_rate_generator
// Module Name:   /home/matheus/ISE_projects/baud_rate_generator/testbench.v
// Project Name:  baud_rate_generator
// Target Device:  
// Tool versions:  
// Description: 
//
// Verilog Test Fixture created by ISE for module: baud_rate_generator
//
// Dependencies:
// 
// Revision:
// Revision 0.01 - File Created
// Additional Comments:
// 
////////////////////////////////////////////////////////////////////////////////

module testbench;

	// Inputs
	reg clk_in;
	reg start;

	// Outputs
	wire clk_0_out;
	wire clk_1_out;
	wire clk_2_out;
	wire clk_3_out;
	wire clk_4_out;
	wire clk_5_out;
	wire clk_6_out;
	wire clk_7_out;

	// Instantiate the Unit Under Test (DUT)
	baud_rate_generator dut (
		.clk_in(clk_in), 
		.start(start), 
		.clk_0_out(clk_0_out), 
		.clk_1_out(clk_1_out), 
		.clk_2_out(clk_2_out), 
		.clk_3_out(clk_3_out), 
		.clk_4_out(clk_4_out), 
		.clk_5_out(clk_5_out), 
		.clk_6_out(clk_6_out), 
		.clk_7_out(clk_7_out)
	);

    initial 
        begin: Clock_generator
          clk_in = 0;
          forever #5 clk_in = ~clk_in;
        end


	initial 
        begin
            // Initialize Inputs
            start = 0;
            #50;
            start = 1;
			#100;
            start = 0;
			#100;
            start = 1;
			#100;

			$finish;
        end
      
    initial 
        begin: Wavedump
            $dumpfile("dump.vcd");
            $dumpvars(0);
        end

endmodule

baud_rate_generator/dump.vcd
$date
	Mon Jan 26 22:24:21 2026
$end
$version
	Icarus Verilog
$end
$timescale
	1ps
$end
$scope module testbench $end
$var wire 1 ! clk_7_out $end
$var wire 1 " clk_6_out $end
$var wire 1 # clk_5_out $end
$var wire 1 $ clk_4_out $end
$var wire 1 % clk_3_out $end
$var wire 1 & clk_2_out $end
$var wire 1 ' clk_1_out $end
$var wire 1 ( clk_0_out $end
$var reg 1 ) clk_in $end
$var reg 1 * start $end
$scope module dut $end
$var wire 1 ) clk_in $end
$var wire 1 * start $end
$var reg 1 ( clk_0_out $end
$var reg 1 ' clk_1_out $end
$var reg 1 & clk_2_out $end
$var reg 1 % clk_3_out $end
$var reg 1 $ clk_4_out $end
$var reg 1 # clk_5_out $end
$var reg 1 " clk_6_out $end
$var reg 1 ! clk_7_out $end
$var reg 8 + clk_sys [7:0] $end
$upscope $end
$scope begin Clock_generator $end
$upscope $end
$scope begin Wavedump $end
$upscope $end
$upscope $end
$enddefinitions $end
$comment Show the parameter values. $end
$dumpall
$end
#0
$dumpvars
bx +
0*
0)
x(
x'
x&
x%
x$
x#
x"
x!
$end
#5000
0!
0"
0#
0$
0%
0&
0'
0(
b0 +
1)
#10000
0)
#15000
1)
#20000
0)
#25000
1)
#30000
0)
#35000
1)
#40000
0)
#45000
1)
#50000
0)
1*
#55000
1(
b1 +
1)
#60000
0)
#65000
1'
0(
b10 +
1)
#70000
0)
#75000
1(
b11 +
1)
#80000
0)
#85000
1&
0'
0(
b100 +
1)
#90000
0)
#95000
1(
b101 +
1)
#100000
0)
#105000
1'
0(
b110 +
1)
#110000
0)
#115000
1(
b111 +
1)
#120000
0)
#125000
1%
0&
0'
0(
b1000 +
1)
#130000
0)
#135000
1(
b1001 +
1)
#140000
0)
#145000
1'
0(
b1010 +
1)
#150000
0)
0*
#155000
0%
0'
b0 +
1)
#160000
0)
#165000
1)
#170000
0)
#175000
1)
#180000
0)
#185000
1)
#190000
0)
#195000
1)
#200000
0)
#205000
1)
#210000
0)
#215000
1)
#220000
0)
#225000
1)
#230000
0)
#235000
1)
#240000
0)
#245000
1)
#250000
0)
1*
#255000
1(
b1 +
1)
#260000
0)
#265000
1'
0(
b10 +
1)
#270000
0)
#275000
1(
b11 +
1)
#280000
0)
#285000
1&
0'
0(
b100 +
1)
#290000
0)
#295000
1(
b101 +
1)
#300000
0)
#305000
1'
0(
b110 +
1)
#310000
0)
#315000
1(
b111 +
1)
#320000
0)
#325000
1%
0&
0'
0(
b1000 +
1)
#330000
0)
#335000
1(
b1001 +
1)
#340000
0)
#345000
1'
0(
b1010 +
1)
