card_stack/card_stack.v
`timescale 1ns / 1ps
//////////////////////////////////////////////////////////////////////////////////
// Company: 
// Engineer: 
// 
// Create Date:    21:46:48 01/27/2026 
// Design Name: 
// Module Name:    buffer_fifo 
// Project Name: 
// Target Devices: 
// Tool versions: 
// Description: 
//
// Dependencies: 
//
// Revision: 
// Revision 0.01 - File Created
// Additional Comments: 
//
//////////////////////////////////////////////////////////////////////////////////

module card_stack(
    input clk_i,
    input save,
    input rst_i,
    input reg [7:0] data_in,

    output reg [7:0] data_out_0,
    output reg [7:0] data_out_1,
    output reg [7:0] data_out_2,
    output reg [7:0] data_out_3,
    output reg [7:0] data_out_4,
    output reg [7:0] data_out_5,
    output reg [7:0] data_out_6,
    output reg [7:0] data_out_7,
    output reg [7:0] data_out_8,
    output reg [7:0] data_out_9,
    output reg [7:0] data_out_10

);
 //Uma por carta recebida:

/*

Para que isso aconteça, você precisaria de uma combinação específica como esta:

4 cartas de valor 1 (Áses) = 4 pontos

4 cartas de valor 2 = 8 pontos (Total: 12)

3 cartas de valor 3 = 9 pontos (Total: 21)

*/

//data_pack:
reg [7:0] data_stack_0;
reg [7:0] data_stack_1;
reg [7:0] data_stack_2;
reg [7:0] data_stack_3;
reg [7:0] data_stack_4;
reg [7:0] data_stack_5;
reg [7:0] data_stack_6;
reg [7:0] data_stack_7;
reg [7:0] data_stack_8;
reg [7:0] data_stack_9;
reg [7:0] data_stack_10;
reg [7:0] data_receiver;

//Contador de cartas, indo de 0 a 10
reg [3:0] cycle_count;

always@(posedge clk_i or negedge rst_i)
    begin
        if(!rst_i)
            begin
                data_stack_0    =  8'b00000000; 
                data_stack_1    =  8'b00000000; 
                data_stack_2    =  8'b00000000; 
                data_stack_3    =  8'b00000000; 
                data_stack_4    =  8'b00000000; 
                data_stack_5    =  8'b00000000; 
                data_stack_6    =  8'b00000000; 
                data_stack_7    =  8'b00000000; 
                data_stack_8    =  8'b00000000; 
                data_stack_9    =  8'b00000000; 
                data_stack_10   =  8'b00000000; 
                cycle_count     =  4'b0000;
            end
        else 
            if(save)
                begin
                    cycle_count = cycle_count + 1'b1;
                    data_receiver = data_in;
                    if(cycle_count == 1) 
                        begin
                            data_stack_0    =  data_receiver;
                        end
                    else 
                    if(cycle_count == 2) 
                        begin
                            data_stack_1    =  data_stack_0;
                            data_stack_0    =  data_receiver;
                        end
                    else 
                    if(cycle_count == 3) 
                        begin
                            data_stack_2    =  data_stack_1;
                            data_stack_1    =  data_stack_0;
                            data_stack_0    =  data_receiver;
                        end
                    else 
                    if(cycle_count == 4) 
                        begin
                            data_stack_3    =  data_stack_2;   
                            data_stack_2    =  data_stack_1;
                            data_stack_1    =  data_stack_0;
                            data_stack_0    =  data_receiver;
                        end
                    else 
                    if(cycle_count == 5) 
                        begin
                            data_stack_4    =  data_stack_3; 
                            data_stack_3    =  data_stack_2;   
                            data_stack_2    =  data_stack_1;
                            data_stack_1    =  data_stack_0;
                            data_stack_0    =  data_receiver;
                        end
                    else 
                    if(cycle_count == 6) 
                        begin
                            data_stack_5    =  data_stack_4; 
                            data_stack_4    =  data_stack_3; 
                            data_stack_3    =  data_stack_2;   
                            data_stack_2    =  data_stack_1;
                            data_stack_1    =  data_stack_0;
                            data_stack_0    =  data_receiver;
                        end
                    else 
                    if(cycle_count == 7) 
                        begin
                            data_stack_6    =  data_stack_5;                      
                            data_stack_5    =  data_stack_4; 
                            data_stack_4    =  data_stack_3; 
                            data_stack_3    =  data_stack_2;   
                            data_stack_2    =  data_stack_1;
                            data_stack_1    =  data_stack_0;
                            data_stack_0    =  data_receiver;
                        end
                    else 
                    if(cycle_count == 8) 
                        begin
                            data_stack_7    =  data_stack_6;                      
                            data_stack_6    =  data_stack_5;                      
                            data_stack_5    =  data_stack_4; 
                            data_stack_4    =  data_stack_3; 
                            data_stack_3    =  data_stack_2;   
                            data_stack_2    =  data_stack_1;
                            data_stack_1    =  data_stack_0;
                            data_stack_0    =  data_receiver;
                        end
                    else 
                    if(cycle_count == 9) 
                        begin
                            data_stack_8    =  data_stack_7;   
                            data_stack_7    =  data_stack_6;                      
                            data_stack_6    =  data_stack_5;                      
                            data_stack_5    =  data_stack_4; 
                            data_stack_4    =  data_stack_3; 
                            data_stack_3    =  data_stack_2;   
                            data_stack_2    =  data_stack_1;
                            data_stack_1    =  data_stack_0;
                            data_stack_0    =  data_receiver;
                        end
                    else 
                    if(cycle_count == 10) 
                        begin
                            data_stack_9    =  data_stack_8;                     
                            data_stack_8    =  data_stack_7;   
                            data_stack_7    =  data_stack_6;                      
                            data_stack_6    =  data_stack_5;                      
                            data_stack_5    =  data_stack_4; 
                            data_stack_4    =  data_stack_3; 
                            data_stack_3    =  data_stack_2;   
                            data_stack_2    =  data_stack_1;
                            data_stack_1    =  data_stack_0;
                            data_stack_0    =  data_receiver;
                        end
                    else 
                    if(cycle_count == 11) 
                        begin
                            data_stack_10   =  data_stack_9;                   
                            data_stack_9    =  data_stack_8;                     
                            data_stack_8    =  data_stack_7;   
                            data_stack_7    =  data_stack_6;                      
                            data_stack_6    =  data_stack_5;                      
                            data_stack_5    =  data_stack_4; 
                            data_stack_4    =  data_stack_3; 
                            data_stack_3    =  data_stack_2;   
                            data_stack_2    =  data_stack_1;
                            data_stack_1    =  data_stack_0;
                            data_stack_0    =  data_receiver;
                        end
                    else 
                        begin
                            data_stack_10   =  data_stack_10;                   
                            data_stack_9    =  data_stack_9;                     
                            data_stack_8    =  data_stack_8;   
                            data_stack_7    =  data_stack_7;                      
                            data_stack_6    =  data_stack_6;                      
                            data_stack_5    =  data_stack_5; 
                            data_stack_4    =  data_stack_4; 
                            data_stack_3    =  data_stack_3;   
                            data_stack_2    =  data_stack_2;
                            data_stack_1    =  data_stack_1;
                            data_stack_0    =  data_stack_0;
                        end
                end
    end

always@(*)
    begin
        data_out_0  = data_stack_0;
        data_out_1  = data_stack_1;
        data_out_2  = data_stack_2;
        data_out_3  = data_stack_3;
        data_out_4  = data_stack_4;
        data_out_5  = data_stack_5;
        data_out_6  = data_stack_6;
        data_out_7  = data_stack_7;
        data_out_8  = data_stack_8;
        data_out_9  = data_stack_9;
        data_out_10 = data_stack_10;
    end

endmodule

card_stack/testbench.v
`timescale 1ns / 1ps

////////////////////////////////////////////////////////////////////////////////
// Company: 
// Engineer:
//
// Create Date:   21:47:26 01/27/2026
// Design Name:   buffer_fifo
// Module Name:   /home/matheus/ISE_projects/buffer_fifo/testbench.v
// Project Name:  buffer_fifo
// Target Device:  
// Tool versions:  
// Description: 
//
// Verilog Test Fixture created by ISE for module: buffer_fifo
//
// Dependencies:
// 
// Revision:
// Revision 0.01 - File Created
// Additional Comments:
// 
////////////////////////////////////////////////////////////////////////////////

module testbench;

	// Inputs
	reg clk_i;
	reg save;
	reg rst_i;
    reg [7:0] data_in;

	// Outputs
	wire [7:0] data_out_0;
	wire [7:0] data_out_1;
	wire [7:0] data_out_2;
	wire [7:0] data_out_3;
	wire [7:0] data_out_4;
	wire [7:0] data_out_5;
	wire [7:0] data_out_6;
	wire [7:0] data_out_7;
	wire [7:0] data_out_8;
	wire [7:0] data_out_9;
	wire [7:0] data_out_10;

	// Instantiate the Unit Under Test (UUT)
	card_stack uut (
		.clk_i(clk_i), 
		.save(save), 
		.rst_i(rst_i), 
		.data_in(data_in),
		.data_out_0(data_out_0), 
		.data_out_1(data_out_1), 
		.data_out_2(data_out_2), 
		.data_out_3(data_out_3), 
		.data_out_4(data_out_4), 
		.data_out_5(data_out_5), 
		.data_out_6(data_out_6), 
		.data_out_7(data_out_7), 
		.data_out_8(data_out_8), 
		.data_out_9(data_out_9), 
		.data_out_10(data_out_10)
	);
	
    initial 
        begin: Clock_generator
          clk_i = 0;
          forever #5 clk_i = ~clk_i;
        end

	initial begin
		rst_i = 0;
		#20;
		rst_i = 1;
		save = 0;
		#25;
		data_in = 8'b00001010;
		save = 1;

		// Wait 100 ns for global reset to finish
		#100;
        
		// Add stimulus here
		$finish;
	end
      
    initial 
        begin: Wavedump
            $dumpfile("dump.vcd");
            $dumpvars(0);
        end

endmodule

card_stack/dump.vcd
$date
	Wed Jan 28 16:07:36 2026
$end
$version
	Icarus Verilog
$end
$timescale
	1ps
$end
$scope module testbench $end
$var wire 8 ! data_out_9 [7:0] $end
$var wire 8 " data_out_8 [7:0] $end
$var wire 8 # data_out_7 [7:0] $end
$var wire 8 $ data_out_6 [7:0] $end
$var wire 8 % data_out_5 [7:0] $end
$var wire 8 & data_out_4 [7:0] $end
$var wire 8 ' data_out_3 [7:0] $end
$var wire 8 ( data_out_2 [7:0] $end
$var wire 8 ) data_out_10 [7:0] $end
$var wire 8 * data_out_1 [7:0] $end
$var wire 8 + data_out_0 [7:0] $end
$var reg 1 , clk_i $end
$var reg 8 - data_in [7:0] $end
$var reg 1 . rst_i $end
$var reg 1 / save $end
$scope module uut $end
$var wire 1 , clk_i $end
$var wire 8 0 data_in [7:0] $end
$var wire 1 . rst_i $end
$var wire 1 / save $end
$var reg 4 1 cycle_count [3:0] $end
$var reg 8 2 data_out_0 [7:0] $end
$var reg 8 3 data_out_1 [7:0] $end
$var reg 8 4 data_out_10 [7:0] $end
$var reg 8 5 data_out_2 [7:0] $end
$var reg 8 6 data_out_3 [7:0] $end
$var reg 8 7 data_out_4 [7:0] $end
$var reg 8 8 data_out_5 [7:0] $end
$var reg 8 9 data_out_6 [7:0] $end
$var reg 8 : data_out_7 [7:0] $end
$var reg 8 ; data_out_8 [7:0] $end
$var reg 8 < data_out_9 [7:0] $end
$var reg 8 = data_receiver [7:0] $end
$var reg 8 > data_stack_0 [7:0] $end
$var reg 8 ? data_stack_1 [7:0] $end
$var reg 8 @ data_stack_10 [7:0] $end
$var reg 8 A data_stack_2 [7:0] $end
$var reg 8 B data_stack_3 [7:0] $end
$var reg 8 C data_stack_4 [7:0] $end
$var reg 8 D data_stack_5 [7:0] $end
$var reg 8 E data_stack_6 [7:0] $end
$var reg 8 F data_stack_7 [7:0] $end
$var reg 8 G data_stack_8 [7:0] $end
$var reg 8 H data_stack_9 [7:0] $end
$upscope $end
$scope begin Clock_generator $end
$upscope $end
$scope begin Wavedump $end
$upscope $end
$upscope $end
$enddefinitions $end
$comment Show the parameter values. $end
$dumpall
$end
#0
$dumpvars
b0 H
b0 G
b0 F
b0 E
b0 D
b0 C
b0 B
b0 A
b0 @
b0 ?
b0 >
bx =
b0 <
b0 ;
b0 :
b0 9
b0 8
b0 7
b0 6
b0 5
b0 4
b0 3
b0 2
b0 1
bx 0
x/
0.
bx -
0,
b0 +
b0 *
b0 )
b0 (
b0 '
b0 &
b0 %
b0 $
b0 #
b0 "
b0 !
$end
#5000
1,
#10000
0,
#15000
1,
#20000
0,
0/
1.
#25000
1,
#30000
0,
#35000
1,
#40000
0,
#45000
b1010 +
b1010 2
b1010 >
b1010 =
b1 1
1,
1/
b1010 -
b1010 0
#50000
0,
#55000
b1010 *
b1010 3
b1010 ?
b10 1
1,
#60000
0,
#65000
b1010 (
b1010 5
b1010 A
b11 1
1,
#70000
0,
#75000
b1010 '
b1010 6
b1010 B
b100 1
1,
#80000
0,
#85000
b1010 &
b1010 7
b1010 C
b101 1
1,
#90000
0,
#95000
b1010 %
b1010 8
b1010 D
b110 1
1,
#100000
0,
#105000
b1010 $
b1010 9
b1010 E
b111 1
1,
#110000
0,
#115000
b1010 #
b1010 :
b1010 F
b1000 1
1,
#120000
0,
#125000
b1010 "
b1010 ;
b1010 G
b1001 1
1,
#130000
0,
#135000
b1010 !
b1010 <
b1010 H
b1010 1
1,
#140000
0,
#145000
b1010 )
b1010 4
b1010 @
b1011 1
1,
